ess_cloud_utils/__init__.py
ess_cloud_utils/apis_client.py
ess_cloud_utils/eureka.py
ess_cloud_utils/host_info_service.py
ess_cloud_utils-0.31.dist-info/LICENSE.txt
ess_cloud_utils-0.31.dist-info/METADATA
ess_cloud_utils-0.31.dist-info/WHEEL
ess_cloud_utils-0.31.dist-info/top_level.txt
ess_cloud_utils-0.31.dist-info/RECORD
